galini/__init__.py
galini/__main__.py
galini/__version__.py
galini/cli.py
galini/error.py
galini/galini.py
galini/ipython.py
galini/math.py
galini/quantities.py
galini/registry.py
galini/suspect.py
galini/telemetry.py
galini/timelimit.py
galini/algorithms/__init__.py
galini/algorithms/algorithm.py
galini/algorithms/registry.py
galini/branch_and_bound/__init__.py
galini/branch_and_bound/algorithm.py
galini/branch_and_bound/branching.py
galini/branch_and_bound/node.py
galini/branch_and_bound/selection.py
galini/branch_and_bound/solution.py
galini/branch_and_bound/strategy.py
galini/branch_and_bound/telemetry.py
galini/branch_and_bound/tree.py
galini/branch_and_cut/__init__.py
galini/branch_and_cut/algorithm.py
galini/branch_and_cut/bound_reduction.py
galini/branch_and_cut/branching.py
galini/branch_and_cut/extensions.py
galini/branch_and_cut/node_storage.py
galini/branch_and_cut/primal.py
galini/branch_and_cut/relaxation.py
galini/branch_and_cut/state.py
galini/commands/__init__.py
galini/commands/command_output.py
galini/commands/commands.py
galini/commands/info.py
galini/commands/plugins.py
galini/commands/solve.py
galini/commands/special_structure.py
galini/config/__init__.py
galini/config/configuration.py
galini/config/manager.py
galini/config/options.py
galini/cuts/__init__.py
galini/cuts/generator.py
galini/cuts/manager.py
galini/cuts/pool.py
galini/io/__init__.py
galini/io/logging.py
galini/io/message.py
galini/io/message_pb2.py
galini/io/reader.py
galini/io/writer.py
galini/outer_approximation/__init__.py
galini/outer_approximation/cuts_generator.py
galini/outer_approximation/feasibility_problem.py
galini/outer_approximation/mixed_integer_cuts_generator.py
galini/outer_approximation/shared.py
galini/pyomo/__init__.py
galini/pyomo/reader.py
galini/pyomo/util.py
galini/relaxations/__init__.py
galini/relaxations/expressions.py
galini/relaxations/multivariate.py
galini/relaxations/relax.py
galini/sdp/NNs.dll
galini/sdp/NNs.so
galini/sdp/__init__.py
galini-1.0.2.dist-info/LICENSE
galini-1.0.2.dist-info/METADATA
galini-1.0.2.dist-info/WHEEL
galini-1.0.2.dist-info/entry_points.txt
galini-1.0.2.dist-info/top_level.txt
galini-1.0.2.dist-info/RECORD
