Metadata-Version: 2.1
Name: galini
Version: 1.0.2
Summary: Mixed Integer Solver
Home-page: UNKNOWN
Author: Francesco Ceccon
Author-email: francesco@ceccon.me
License: Apache 2.0
Platform: UNKNOWN
License-File: LICENSE
Requires-Dist: pyomo (>=5.6.7)
Requires-Dist: cog-suspect (>=2.1.2)
Requires-Dist: numpy (>=1.15)
Requires-Dist: toml
Requires-Dist: pydot
Requires-Dist: texttable (>=1.4.0)
Requires-Dist: pytimeparse (>=1.1.8)
Requires-Dist: protobuf (>=3.0)
Requires-Dist: h5py (>=2.0)
Requires-Dist: networkx (>=2.4)
Requires-Dist: coramin (>=0.1.0)
Requires-Dist: scipy (>=1.5.2)
